ATI/__init__.py
ATI/main.py
atibotlog-0.1.4.dist-info/LICENSE
atibotlog-0.1.4.dist-info/METADATA
atibotlog-0.1.4.dist-info/WHEEL
atibotlog-0.1.4.dist-info/top_level.txt
atibotlog-0.1.4.dist-info/RECORD
