Metadata-Version: 2.2
Name: atibotlog
Version: 0.1.4
Summary: A Python package for bot automation and database logging.
Author: Shibli M.S
Classifier: Programming Language :: Python :: 3
Classifier: License :: OSI Approved :: MIT License
Classifier: Operating System :: OS Independent
Requires-Python: >=3.12
License-File: LICENSE
Requires-Dist: pandas
Requires-Dist: pyodbc
Requires-Dist: sqlalchemy
Dynamic: author
Dynamic: classifier
Dynamic: description
Dynamic: description-content-type
Dynamic: requires-dist
Dynamic: requires-python
Dynamic: summary
